fastapi_vite_assets/__init__.py
fastapi_vite_assets/config.py
fastapi_vite_assets/integration.py
fastapi_vite_assets/logger.py
fastapi_vite_assets/manifest.py
fastapi_vite_assets/py.typed
fastapi_vite_assets/template_helpers.py
fastapi_vite_assets-0.2.0.dist-info/METADATA
fastapi_vite_assets-0.2.0.dist-info/WHEEL
fastapi_vite_assets-0.2.0.dist-info/licenses/LICENSE
fastapi_vite_assets-0.2.0.dist-info/RECORD
