Metadata-Version: 2.4
Name: fastapi-vite-assets
Version: 0.2.0
Summary: Vite asset management for FastAPI with Jinja2 templates
Project-URL: Homepage, https://github.com/jkupcho/fastapi-vite-assets
Project-URL: Documentation, https://github.com/jkupcho/fastapi-vite-assets/blob/main/packages/fastapi-vite-assets/README.md
Project-URL: Repository, https://github.com/jkupcho/fastapi-vite-assets
Project-URL: Issues, https://github.com/jkupcho/fastapi-vite-assets/issues
Author-email: Jonathan Kupcho <jonathan.kupcho@gmail.com>
License: MIT
License-File: LICENSE
Keywords: assets,fastapi,frontend,hmr,jinja2,vite
Classifier: Development Status :: 3 - Alpha
Classifier: Framework :: FastAPI
Classifier: Intended Audience :: Developers
Classifier: License :: OSI Approved :: MIT License
Classifier: Programming Language :: Python :: 3
Classifier: Programming Language :: Python :: 3.10
Classifier: Programming Language :: Python :: 3.11
Classifier: Programming Language :: Python :: 3.12
Classifier: Programming Language :: Python :: 3.13
Classifier: Topic :: Internet :: WWW/HTTP :: Dynamic Content
Classifier: Topic :: Software Development :: Libraries :: Python Modules
Classifier: Typing :: Typed
Requires-Python: >=3.10
Requires-Dist: fastapi>=0.100.0
Requires-Dist: jinja2>=3.1.0
Provides-Extra: dev
Requires-Dist: commitizen>=3.13.0; extra == 'dev'
Requires-Dist: mypy>=1.0.0; extra == 'dev'
Requires-Dist: pre-commit>=3.0.0; extra == 'dev'
Requires-Dist: pytest-cov>=4.0.0; extra == 'dev'
Requires-Dist: pytest>=7.0.0; extra == 'dev'
Requires-Dist: ruff>=0.8.0; extra == 'dev'
